scpidev/__init__.py
scpidev/command.py
scpidev/device.py
scpidev/keyword.py
scpidev/parameter.py
scpidev/utils.py
scpidev/value.py
scpidev-0.0.1a0.dist-info/LICENSE
scpidev-0.0.1a0.dist-info/METADATA
scpidev-0.0.1a0.dist-info/WHEEL
scpidev-0.0.1a0.dist-info/top_level.txt
scpidev-0.0.1a0.dist-info/RECORD
