Metadata-Version: 2.1
Name: scpidev
Version: 0.0.1a0
Summary: A python package to turn your device into an SCPI end point
Home-page: https://github.com/mrberti/pyscpidev
Author: Simon Bertling
Author-email: simon.bertling@gmx.de
License: MIT
Platform: UNKNOWN
